COPYRIGHT.txt
LICENSE.txt
README.txt
bootstrap.py
buildout.cfg
setup.py
Products/__init__.py
Products.LDAPConnector.egg-info/PKG-INFO
Products.LDAPConnector.egg-info/SOURCES.txt
Products.LDAPConnector.egg-info/dependency_links.txt
Products.LDAPConnector.egg-info/entry_points.txt
Products.LDAPConnector.egg-info/namespace_packages.txt
Products.LDAPConnector.egg-info/not-zip-safe
Products.LDAPConnector.egg-info/requires.txt
Products.LDAPConnector.egg-info/top_level.txt
Products/LDAPConnector/CHANGES.txt
Products/LDAPConnector/INSTALL.txt
Products/LDAPConnector/LDAPConnector.py
Products/LDAPConnector/README.txt
Products/LDAPConnector/VERSION.txt
Products/LDAPConnector/__init__.py
Products/LDAPConnector/configure.zcml
Products/LDAPConnector/exportimport.py
Products/LDAPConnector/utils.py
Products/LDAPConnector/browser/__init__.py
Products/LDAPConnector/browser/cache.py
Products/LDAPConnector/browser/configuration.py
Products/LDAPConnector/browser/configure.zcml
Products/LDAPConnector/browser/search.py
Products/LDAPConnector/browser/servers.py
Products/LDAPConnector/browser/testing.zcml
Products/LDAPConnector/browser/templates/cache.pt
Products/LDAPConnector/browser/templates/configuration.pt
Products/LDAPConnector/browser/templates/search.pt
Products/LDAPConnector/browser/templates/servers.pt
Products/LDAPConnector/browser/tests/__init__.py
Products/LDAPConnector/browser/tests/base.py
Products/LDAPConnector/browser/tests/test_cache.py
Products/LDAPConnector/browser/tests/test_configuration.py
Products/LDAPConnector/browser/tests/test_search.py
Products/LDAPConnector/browser/tests/test_servers.py
Products/LDAPConnector/profiles/__init__.py
Products/LDAPConnector/profiles/configure.zcml
Products/LDAPConnector/tests/__init__.py
Products/LDAPConnector/tests/dummy.py
Products/LDAPConnector/tests/test_LDAPConnector.py
Products/LDAPConnector/tests/test_exportimport.py
Products/LDAPConnector/tests/test_utils.py
Products/LDAPConnector/upgrade/__init__.py
Products/LDAPConnector/upgrade/configure.zcml
Products/LDAPConnector/www/add.pt
Products/LDAPConnector/www/ldapconnector.gif
Products/LDAPConnector/xml/ldapconnector.xml
docs/Makefile
docs/Products.LDAPConnector.pdf
docs/api.rst
docs/changes.rst
docs/conf.py
docs/development.rst
docs/glossary.rst
docs/index.rst
docs/install.rst
docs/screen01.png
docs/screen02.png
docs/screen03.png
docs/screen04.png
