Metadata-Version: 1.0
Name: Products.LDAPConnector
Version: 1.0
Summary: Persistent Zope 2 LDAP connection manager
Home-page: http://pypi.python.org/pypi/Products.LDAPConnector
Author: Jens Vagelpohl and contributors
Author-email: jens@dataflake.org
License: ZPL 2.1 (http://www.zope.org/Resources/License/ZPL-2.1)
Keywords: web application server zope zope2 ldap
Platform: UNKNOWN
Classifier: Development Status :: 5 - Production/Stable
Classifier: Framework :: Zope2
Classifier: Intended Audience :: Developers
Classifier: License :: OSI Approved :: Zope Public License
Classifier: Programming Language :: Python
Classifier: Topic :: Internet :: WWW/HTTP :: Site Management
Classifier: Topic :: Software Development
Classifier: Topic :: System :: Systems Administration :: Authentication/Directory :: LDAP
